MANIFEST.in
README.md
setup.py
blingtron/__init__.py
blingtron/blingtron.py
blingtron/config.py
blingtron.egg-info/PKG-INFO
blingtron.egg-info/SOURCES.txt
blingtron.egg-info/dependency_links.txt
blingtron.egg-info/entry_points.txt
blingtron.egg-info/requires.txt
blingtron.egg-info/top_level.txt
blingtron/core/__init__.py
blingtron/core/blingrc.py
blingtron/core/commands.py
blingtron/core/io.py
blingtron/core/lock.py
blingtron/core/utils.py
blingtron/domain/__init__.py
blingtron/domain/blingrc.py
blingtron/domain/vendor.py
blingtron/vendor/__init__.py
blingtron/vendor/docker.py
blingtron/vendor/git.py
blingtron/vendor/packer.py
blingtron/vendor/travis.py