Metadata-Version: 1.1
Name: blingtron
Version: 0.1.1
Summary: Blingtron is a simple CLI tool aimed at helping developers run their II projects.
Home-page: https://github.com/ImageIntelligence/blingtron
Author: David Vuong
Author-email: david@imageintelligence.com
License: UNKNOWN
Platform: UNKNOWN
Classifier: Intended Audience :: Developers
Classifier: Environment :: Console
Classifier: Topic :: Utilities
Classifier: Programming Language :: Python :: 2 :: Only
Classifier: Programming Language :: Python :: 2.6
Classifier: Programming Language :: Python :: 2.7
